shushi/__init__.py
shushi/__version__.py
shushi/api.py
shushi/cli.py
shushi/constants.py
shushi/core.py
shushi/crypto.py
shushi/data.py
shushi/exceptions.py
shushi/record.py
shushi-0.1.0.dist-info/LICENSE
shushi-0.1.0.dist-info/METADATA
shushi-0.1.0.dist-info/WHEEL
shushi-0.1.0.dist-info/entry_points.txt
shushi-0.1.0.dist-info/top_level.txt
shushi-0.1.0.dist-info/RECORD
