Metadata-Version: 2.1
Name: shushi
Version: 0.1.0
Summary: Minimalist secrets management in Python
Home-page: https://github.com/alexmacniven/shushi
Author: Alex Macniven
Author-email: macniven.ap@gmail.com
License: MIT
Platform: UNKNOWN
Requires-Python: >=3.7.0
Requires-Dist: click
Requires-Dist: cryptography
Provides-Extra: dev
Requires-Dist: pytest ; extra == 'dev'
Requires-Dist: pytest-mock ; extra == 'dev'
Requires-Dist: rope ; extra == 'dev'
Requires-Dist: flake8 ; extra == 'dev'
Requires-Dist: coverage ; extra == 'dev'
Requires-Dist: twine ; extra == 'dev'
